WADSeg/__init__.py
WADSeg/wadseg.py
wadseg-1.5.dist-info/licenses/LICENSE
wadseg-1.5.dist-info/METADATA
wadseg-1.5.dist-info/WHEEL
wadseg-1.5.dist-info/top_level.txt
wadseg-1.5.dist-info/RECORD
