Metadata-Version: 2.4
Name: wadseg
Version: 1.5
Summary: This is a implementation of WADSeg
Home-page: https://github.com/qufy6/wadseg
Author: Feiyu Qu
Author-email: qufy66@gmail.com
Classifier: Programming Language :: Python :: 3
Classifier: License :: OSI Approved :: MIT License
Classifier: Operating System :: OS Independent
Requires-Python: >=3.6
License-File: LICENSE
Requires-Dist: transformers
Requires-Dist: torch
Requires-Dist: matplotlib
Requires-Dist: matplotlib
Requires-Dist: numpy
Requires-Dist: seaborn
Requires-Dist: spacy
Requires-Dist: ipython
Dynamic: author
Dynamic: author-email
Dynamic: classifier
Dynamic: description
Dynamic: description-content-type
Dynamic: home-page
Dynamic: license-file
Dynamic: requires-dist
Dynamic: requires-python
Dynamic: summary
